CHANGELOG.rst
LICENSE
bquest/__init__.py
bquest/dataframe.py
bquest/runner.py
bquest/tables.py
bquest/util.py
bquest-0.5.7.dist-info/METADATA
bquest-0.5.7.dist-info/WHEEL
bquest-0.5.7.dist-info/licenses/LICENSE
bquest-0.5.7.dist-info/RECORD
