Metadata-Version: 2.4
Name: bquest
Version: 0.5.7
Summary: Effortlessly validate and test your Google BigQuery queries with the power of pandas DataFrames in Python.
Project-URL: Repository, https://github.com/ottogroup/bquest
Project-URL: Documentation, https://ottogroup.github.io/bquest/
Project-URL: Issues, https://github.com/ottogroup/bquest/issues
Project-URL: Releases, https://github.com/ottogroup/bquest/releases
Author: Otto Group data.works GmbH
License-Expression: Apache-2.0
License-File: LICENSE
Keywords: google-big-query,open-source,pandas,query,sql,testing
Classifier: Development Status :: 4 - Beta
Classifier: Environment :: Console
Classifier: Intended Audience :: Developers
Classifier: Intended Audience :: Information Technology
Classifier: Intended Audience :: Science/Research
Classifier: Intended Audience :: System Administrators
Classifier: License :: OSI Approved :: Apache Software License
Classifier: Operating System :: MacOS
Classifier: Operating System :: POSIX
Classifier: Operating System :: Unix
Classifier: Programming Language :: Python
Classifier: Programming Language :: Python :: 3
Classifier: Programming Language :: Python :: 3.10
Classifier: Programming Language :: Python :: 3.11
Classifier: Programming Language :: Python :: 3.12
Classifier: Topic :: Database
Classifier: Topic :: Internet
Classifier: Topic :: Software Development :: Libraries
Classifier: Topic :: Software Development :: Testing :: Unit
Classifier: Topic :: Utilities
Requires-Python: <4.0,>=3.10
Requires-Dist: google-cloud-bigquery[bqstorage,pandas]>=3.8
Requires-Dist: pandas-gbq>=0.19
Requires-Dist: pandas>=2.0
Requires-Dist: sqlvalidator>=0.0.20
